azure/keyvault/keys/__init__.py
azure/keyvault/keys/_client.py
azure/keyvault/keys/_enums.py
azure/keyvault/keys/_models.py
azure/keyvault/keys/_sdk_moniker.py
azure/keyvault/keys/_version.py
azure/keyvault/keys/py.typed
azure/keyvault/keys/_generated/__init__.py
azure/keyvault/keys/_generated/_client.py
azure/keyvault/keys/_generated/_configuration.py
azure/keyvault/keys/_generated/_patch.py
azure/keyvault/keys/_generated/_serialization.py
azure/keyvault/keys/_generated/_vendor.py
azure/keyvault/keys/_generated/py.typed
azure/keyvault/keys/_generated/_operations/__init__.py
azure/keyvault/keys/_generated/_operations/_operations.py
azure/keyvault/keys/_generated/_operations/_patch.py
azure/keyvault/keys/_generated/aio/__init__.py
azure/keyvault/keys/_generated/aio/_client.py
azure/keyvault/keys/_generated/aio/_configuration.py
azure/keyvault/keys/_generated/aio/_patch.py
azure/keyvault/keys/_generated/aio/_vendor.py
azure/keyvault/keys/_generated/aio/_operations/__init__.py
azure/keyvault/keys/_generated/aio/_operations/_operations.py
azure/keyvault/keys/_generated/aio/_operations/_patch.py
azure/keyvault/keys/_generated/models/__init__.py
azure/keyvault/keys/_generated/models/_enums.py
azure/keyvault/keys/_generated/models/_models.py
azure/keyvault/keys/_generated/models/_patch.py
azure/keyvault/keys/_shared/__init__.py
azure/keyvault/keys/_shared/_polling.py
azure/keyvault/keys/_shared/_polling_async.py
azure/keyvault/keys/_shared/async_challenge_auth_policy.py
azure/keyvault/keys/_shared/async_client_base.py
azure/keyvault/keys/_shared/challenge_auth_policy.py
azure/keyvault/keys/_shared/client_base.py
azure/keyvault/keys/_shared/http_challenge.py
azure/keyvault/keys/_shared/http_challenge_cache.py
azure/keyvault/keys/aio/__init__.py
azure/keyvault/keys/aio/_client.py
azure/keyvault/keys/crypto/__init__.py
azure/keyvault/keys/crypto/_client.py
azure/keyvault/keys/crypto/_enums.py
azure/keyvault/keys/crypto/_key_validity.py
azure/keyvault/keys/crypto/_models.py
azure_keyvault_keys-4.9.0.dist-info/LICENSE
azure_keyvault_keys-4.9.0.dist-info/METADATA
azure_keyvault_keys-4.9.0.dist-info/WHEEL
azure_keyvault_keys-4.9.0.dist-info/top_level.txt
azure_keyvault_keys-4.9.0.dist-info/RECORD
